{
  "current_name": "8008",
  "8008": {
    "btn_non_transparent_std_pic_font_color": "E9ECF0",
    "btn_non_transparent_hvr_pic_font_color": "2E343D",
    "btn_non_transparent_std_bg_color": "2E343D",
    "btn_non_transparent_hvr_bg_color": "E9ECF0",
    "btn_non_transparent_sltctd_border_color": "F44C7F",
    "btn_transparent_std_pic_font_color": "939EAE",
    "btn_transparent_hvr_pic_font_color": "E9ECF0",
    "btn_transparent_sltctd_std_pic_font_color": "F44C7F",
    "btn_transparent_sltctd_hvr_pic_font_color": "E9ECF0",
    "main_border_color": "F44C7F",
    "main_bg_color": "333A45",
    "check_mark_color": "F44C7F",
    "checkbox_font_color": "E9ECF0",
    "checkbox_bg_color": "2E343D",
    "highlight_text_color": "F44C7F",
    "highlighted_text_color": "2E343D",
    "line_edit_bg_color": "2E343D",
    "line_edit_text_color": "E9ECF0",
    "line_edit_placeholdertext_color": "939EAE",
    "typing_text_color": "939EAE",
    "typing_correct_text_color": "E9ECF0",
    "typing_incorrect_text_color": "CC3233",
    "typing_caret_color": "F44C7F",
    "minimize_bg_hvr_color": "74859E",
    "timer_font_color": "F44C7F",
    "logo_font_color": "E9ECF0",
    "logo_icon_color": "F44C7F",
    "counter_font_color": "F44C7F",
    "register_login_font_color": "E9ECF0",
    "correct_text_color": "E9ECF0",
    "incorrect_text_color": "DA3333",
    "default_text_color": "939EAE",
    "caret_text_color": "F44C7F",
    "text_browser_bg_color": "333A45",
    "custom_frame_bg_color": "333A45",
    "custom_frame_font_color": "939EAE",
    "custom_frame_hvr_bg_color": "E9ECF0"
  },
  "current": {
    "btn_non_transparent_std_pic_font_color": "E9ECF0",
    "btn_non_transparent_hvr_pic_font_color": "2E343D",
    "btn_non_transparent_std_bg_color": "2E343D",
    "btn_non_transparent_hvr_bg_color": "E9ECF0",
    "btn_non_transparent_sltctd_border_color": "F44C7F",
    "btn_transparent_std_pic_font_color": "939EAE",
    "btn_transparent_hvr_pic_font_color": "E9ECF0",
    "btn_transparent_sltctd_std_pic_font_color": "F44C7F",
    "btn_transparent_sltctd_hvr_pic_font_color": "E9ECF0",
    "main_border_color": "F44C7F",
    "main_bg_color": "333A45",
    "check_mark_color": "F44C7F",
    "checkbox_font_color": "E9ECF0",
    "checkbox_bg_color": "2E343D",
    "highlight_text_color": "F44C7F",
    "highlighted_text_color": "2E343D",
    "line_edit_bg_color": "2E343D",
    "line_edit_text_color": "E9ECF0",
    "line_edit_placeholdertext_color": "939EAE",
    "typing_text_color": "939EAE",
    "typing_correct_text_color": "E9ECF0",
    "typing_incorrect_text_color": "CC3233",
    "typing_caret_color": "F44C7F",
    "minimize_bg_hvr_color": "74859E",
    "timer_font_color": "F44C7F",
    "logo_font_color": "E9ECF0",
    "logo_icon_color": "F44C7F",
    "counter_font_color": "F44C7F",
    "register_login_font_color": "E9ECF0",
    "correct_text_color": "E9ECF0",
    "incorrect_text_color": "DA3333",
    "default_text_color": "939EAE",
    "caret_text_color": "F44C7F",
    "text_browser_bg_color": "333A45",
    "custom_frame_bg_color": "333A45",
    "custom_frame_font_color": "939EAE",
    "custom_frame_hvr_bg_color": "E9ECF0"
  },
  "creamsicle": {
    "btn_non_transparent_std_pic_font_color": "FCFCF8",
    "btn_non_transparent_hvr_pic_font_color": "FE8954",
    "btn_non_transparent_std_bg_color": "FE8954",
    "btn_non_transparent_hvr_bg_color": "FCFCF8",
    "btn_non_transparent_sltctd_border_color": "FCFCF8",
    "btn_transparent_std_pic_font_color": "FF661F",
    "btn_transparent_hvr_pic_font_color": "FCFCF8",
    "btn_transparent_sltctd_std_pic_font_color": "FCFCF8",
    "btn_transparent_sltctd_hvr_pic_font_color": "FCFCF8",
    "main_border_color": "FCFCF8",
    "main_bg_color": "FF9869",
    "check_mark_color": "FCFCF8",
    "checkbox_font_color": "FCFCF8",
    "checkbox_bg_color": "FE8954",
    "highlight_text_color": "FCFCF8",
    "highlighted_text_color": "FE8954",
    "line_edit_bg_color": "FE8954",
    "line_edit_text_color": "FCFCF8",
    "line_edit_placeholdertext_color": "FF661F",
    "typing_text_color": "FF661F",
    "typing_correct_text_color": "FCFCF8",
    "typing_incorrect_text_color": "7D1FA4",
    "typing_caret_color": "FCFCF8",
    "minimize_bg_hvr_color": "FE8954",
    "timer_font_color": "FCFCF8",
    "logo_font_color": "FCFCF8",
    "logo_icon_color": "FCFCF8",
    "counter_font_color": "FCFCF8",
    "register_login_font_color": "FCFCF8",
    "correct_text_color": "FCFCF8",
    "incorrect_text_color": "6A0DAD",
    "default_text_color": "FF661F",
    "caret_text_color": "FCFCF8",
    "text_browser_bg_color": "FF9869",
    "custom_frame_bg_color": "FF9869",
    "custom_frame_font_color": "FF661F",
    "custom_frame_hvr_bg_color": "FCFCF8"
  },
  "earthsong": {
    "btn_non_transparent_std_pic_font_color": "E6C7A8",
    "btn_non_transparent_hvr_pic_font_color": "1D1B18",
    "btn_non_transparent_std_bg_color": "1D1B18",
    "btn_non_transparent_hvr_bg_color": "E6C7A8",
    "btn_non_transparent_sltctd_border_color": "509452",
    "btn_transparent_std_pic_font_color": "F5AE2D",
    "btn_transparent_hvr_pic_font_color": "E6C7A8",
    "btn_transparent_sltctd_std_pic_font_color": "509452",
    "btn_transparent_sltctd_hvr_pic_font_color": "E6C7A8",
    "main_border_color": "509452",
    "main_bg_color": "292521",
    "check_mark_color": "509452",
    "checkbox_font_color": "E6C7A8",
    "checkbox_bg_color": "292521",
    "highlight_text_color": "509452",
    "highlighted_text_color": "1D1B18",
    "line_edit_bg_color": "1D1B18",
    "line_edit_text_color": "E6C7A8",
    "line_edit_placeholdertext_color": "F5AE2D",
    "typing_text_color": "F5AE2D",
    "typing_correct_text_color": "E6C7A8",
    "typing_incorrect_text_color": "7E2A33",
    "typing_caret_color": "1297B8",
    "minimize_bg_hvr_color": "1D1B18",
    "timer_font_color": "509452",
    "logo_font_color": "E6C7A8",
    "logo_icon_color": "509452",
    "counter_font_color": "509452",
    "register_login_font_color": "E6C7A8",
    "correct_text_color": "E6C7A8",
    "incorrect_text_color": "7E2A33",
    "default_text_color": "F5AE2D",
    "caret_text_color": "FCFCF8",
    "text_browser_bg_color": "292521",
    "custom_frame_bg_color": "292521",
    "custom_frame_font_color": "F5AE2D",
    "custom_frame_hvr_bg_color": "E6C7A8"
  }
}
